keepsafe/__init__.py
keepsafe/core.py
keepsafe-0.0.1.dist-info/LICENSE
keepsafe-0.0.1.dist-info/METADATA
keepsafe-0.0.1.dist-info/WHEEL
keepsafe-0.0.1.dist-info/top_level.txt
keepsafe-0.0.1.dist-info/RECORD
