Metadata-Version: 2.1
Name: keepsafe
Version: 0.0.1
Summary: Keepsafe: Securely store and distribute sensitive information like passwords and keys.
Home-page: https://github.com/muhammad-fiaz/keepsafe
Author: Muhammad Fiaz
Author-email: contact@muhammadfiaz.com
License: MIT License
Project-URL: Source Code, https://github.com/muhammad-fiaz/keepsafe
Project-URL: Bug Tracker, https://github.com/muhammad-fiaz/keepsafe/issues
Project-URL: Documentation, https://github.com/muhammad-fiaz/keepsafe#readme
Classifier: Development Status :: 1 - Planning
Classifier: Intended Audience :: Developers
Classifier: Programming Language :: Python :: 3
Classifier: License :: OSI Approved :: MIT License
Classifier: Operating System :: Unix
Classifier: Operating System :: MacOS :: MacOS X
Classifier: Operating System :: Microsoft :: Windows
Requires-Python: >=3.8
License-File: LICENSE
Requires-Dist: cryptography
Requires-Dist: pytest
